cloudml_hackathon_tensorboard-1.0.dist-info/DESCRIPTION.rst
cloudml_hackathon_tensorboard-1.0.dist-info/METADATA
cloudml_hackathon_tensorboard-1.0.dist-info/RECORD
cloudml_hackathon_tensorboard-1.0.dist-info/WHEEL
cloudml_hackathon_tensorboard-1.0.dist-info/entry_points.txt
cloudml_hackathon_tensorboard-1.0.dist-info/metadata.json
cloudml_hackathon_tensorboard-1.0.dist-info/top_level.txt
external/__init__.py
external/org_html5lib/__init__.py
external/org_html5lib/html5lib/__init__.py
external/org_html5lib/html5lib/constants.py
external/org_html5lib/html5lib/html5parser.py
external/org_html5lib/html5lib/ihatexml.py
external/org_html5lib/html5lib/inputstream.py
external/org_html5lib/html5lib/sanitizer.py
external/org_html5lib/html5lib/tokenizer.py
external/org_html5lib/html5lib/utils.py
external/org_html5lib/html5lib/filters/__init__.py
external/org_html5lib/html5lib/filters/_base.py
external/org_html5lib/html5lib/filters/alphabeticalattributes.py
external/org_html5lib/html5lib/filters/inject_meta_charset.py
external/org_html5lib/html5lib/filters/lint.py
external/org_html5lib/html5lib/filters/optionaltags.py
external/org_html5lib/html5lib/filters/sanitizer.py
external/org_html5lib/html5lib/filters/whitespace.py
external/org_html5lib/html5lib/serializer/__init__.py
external/org_html5lib/html5lib/serializer/htmlserializer.py
external/org_html5lib/html5lib/tests/__init__.py
external/org_html5lib/html5lib/tests/mockParser.py
external/org_html5lib/html5lib/tests/support.py
external/org_html5lib/html5lib/tests/test_encoding.py
external/org_html5lib/html5lib/tests/test_parser.py
external/org_html5lib/html5lib/tests/test_parser2.py
external/org_html5lib/html5lib/tests/test_sanitizer.py
external/org_html5lib/html5lib/tests/test_serializer.py
external/org_html5lib/html5lib/tests/test_stream.py
external/org_html5lib/html5lib/tests/test_tokenizer.py
external/org_html5lib/html5lib/tests/test_treeadapters.py
external/org_html5lib/html5lib/tests/test_treewalkers.py
external/org_html5lib/html5lib/tests/test_whitespace_filter.py
external/org_html5lib/html5lib/tests/tokenizertotree.py
external/org_html5lib/html5lib/tests/performance/__init__.py
external/org_html5lib/html5lib/tests/performance/concatenation.py
external/org_html5lib/html5lib/treeadapters/__init__.py
external/org_html5lib/html5lib/treeadapters/sax.py
